demandforge/__init__.py
demandforge/load_projection.py
demandforge-0.1.0.dist-info/licenses/LICENCE.md
demandforge-0.1.0.dist-info/METADATA
demandforge-0.1.0.dist-info/WHEEL
demandforge-0.1.0.dist-info/top_level.txt
demandforge-0.1.0.dist-info/RECORD
