Metadata-Version: 2.4
Name: demandforge
Version: 0.1.0
Summary: Country level electricity load analysis and projection
Author-email: Yassine Abdelouadoud <yassine.abdelouadoud@minesparis.psl.eu>
Maintainer-email: Yassine Abdelouadoud <yassine.abdelouadoud@minesparis.psl.eu>
License-Expression: MIT
Classifier: Development Status :: 3 - Alpha
Classifier: Operating System :: MacOS :: MacOS X
Classifier: Operating System :: Microsoft :: Windows
Classifier: Operating System :: POSIX :: Linux
Classifier: Programming Language :: Python :: 3.10
Classifier: Programming Language :: Python :: 3.11
Classifier: Programming Language :: Python :: 3.12
Classifier: Programming Language :: Python :: 3.13
Classifier: Topic :: Scientific/Engineering :: Physics
Requires-Python: <4.0.0,>=3.10
License-File: LICENCE.md
Requires-Dist: pandas
Requires-Dist: pyarrow
Provides-Extra: workflow
Requires-Dist: xarray; extra == "workflow"
Requires-Dist: cdsapi; extra == "workflow"
Requires-Dist: polars; extra == "workflow"
Requires-Dist: h5netcdf; extra == "workflow"
Requires-Dist: entsoe-py; extra == "workflow"
Requires-Dist: python-dotenv; extra == "workflow"
Requires-Dist: snakemake; extra == "workflow"
Requires-Dist: google-cloud-storage; extra == "workflow"
Provides-Extra: notebooks
Requires-Dist: notebook; extra == "notebooks"
Requires-Dist: ipykernel; extra == "notebooks"
Requires-Dist: ipython; extra == "notebooks"
Requires-Dist: nbformat; extra == "notebooks"
Requires-Dist: matplotlib; extra == "notebooks"
Requires-Dist: seaborn; extra == "notebooks"
Dynamic: license-file
